Metadata-Version: 1.0
Name: helios1101-gaussian-distributions
Version: 0.1
Summary: Gaussian distributions
Home-page: UNKNOWN
Author: Harshit Singh
Author-email: harshit@codeasylums.com
License: UNKNOWN
Platform: UNKNOWN
